{
  "selection_reason": "best walk-forward tuple (expectancy_r, profit_factor, -max_drawdown_r, macro_f1, weighted_f1, coverage_ratio) with coverage floor",
  "selected_label_params": {
    "future_horizon": 18,
    "tp_mult": 1.8,
    "sl_mult": 1.2,
    "min_move_atr": 0.35,
    "neutral_margin_atr": 0.05
  },
  "selected_label_config_hash": "f87e9956c3c96d7a38254acf479423f05552a5b7fd76dbb6d78fa442ec4d46c3",
  "feature_contract": {
    "feature_count": 25,
    "sequence_length": 24,
    "feature_columns": [
      "Open",
      "High",
      "Low",
      "Close",
      "Volume",
      "RSI",
      "ATR",
      "MACD_Main",
      "MACD_Signal",
      "Bands_Upper",
      "Bands_Lower",
      "Stoch_Main",
      "Stoch_Signal",
      "ADX_Main",
      "ADX_PlusDI",
      "ADX_MinusDI",
      "RSI_H4",
      "MA_H4",
      "RSI_M15",
      "ATR_M15",
      "Hour_Sin",
      "Hour_Cos",
      "DayOfWeek_Sin",
      "DayOfWeek_Cos",
      "Daily_Trend_Proxy"
    ]
  },
  "feature_contract_hash": "3e4b29a628e09d925011eb052358fd32a1a863a863946297b6669730a8e88bce",
  "booster_feature_contract": {
    "feature_count": 30,
    "feature_columns": [
      "base_prob_down",
      "base_prob_sideways",
      "base_prob_up",
      "base_confidence",
      "base_confidence_gap",
      "last_Open",
      "last_High",
      "last_Low",
      "last_Close",
      "last_Volume",
      "last_RSI",
      "last_ATR",
      "last_MACD_Main",
      "last_MACD_Signal",
      "last_Bands_Upper",
      "last_Bands_Lower",
      "last_Stoch_Main",
      "last_Stoch_Signal",
      "last_ADX_Main",
      "last_ADX_PlusDI",
      "last_ADX_MinusDI",
      "last_RSI_H4",
      "last_MA_H4",
      "last_RSI_M15",
      "last_ATR_M15",
      "last_Hour_Sin",
      "last_Hour_Cos",
      "last_DayOfWeek_Sin",
      "last_DayOfWeek_Cos",
      "last_Daily_Trend_Proxy"
    ]
  },
  "label_sweep_reports": [
    {
      "label_params": {
        "future_horizon": 18,
        "tp_mult": 1.8,
        "sl_mult": 1.2,
        "min_move_atr": 0.35,
        "neutral_margin_atr": 0.05
      },
      "label_config_hash": "f87e9956c3c96d7a38254acf479423f05552a5b7fd76dbb6d78fa442ec4d46c3",
      "feature_contract_hash": "3e4b29a628e09d925011eb052358fd32a1a863a863946297b6669730a8e88bce",
      "class_histogram": {
        "0": 19630,
        "1": 945,
        "2": 14384
      },
      "summary": {
        "mean_accuracy": 0.48026315789473684,
        "mean_macro_f1": 0.32936512173825105,
        "mean_weighted_f1": 0.48139526025557344,
        "mean_expectancy_r": 0.5505351622372899,
        "mean_profit_factor": 2.799741100323625,
        "mean_max_drawdown_r": 13.166666666666664,
        "mean_trade_count": 232.0,
        "mean_confidence_ge_threshold_ratio": 0.048436308161708616
      },
      "summary_tuple": [
        0.5505351622372899,
        2.799741100323625,
        -13.166666666666664,
        0.32936512173825105,
        0.48139526025557344,
        0.048436308161708616,
        232.0
      ]
    },
    {
      "label_params": {
        "future_horizon": 24,
        "tp_mult": 2.0,
        "sl_mult": 1.5,
        "min_move_atr": 0.5,
        "neutral_margin_atr": 0.08
      },
      "label_config_hash": "f66ad4634d5cd4b3a1bde7394e42486f7255f3d89c92f311204a63aef0db4496",
      "feature_contract_hash": "3e4b29a628e09d925011eb052358fd32a1a863a863946297b6669730a8e88bce",
      "class_histogram": {
        "0": 19097,
        "1": 793,
        "2": 15063
      },
      "summary": {
        "mean_accuracy": 0.4450696166316994,
        "mean_macro_f1": 0.30735529108638393,
        "mean_weighted_f1": 0.4402053240203111,
        "mean_expectancy_r": 0.32529780467738656,
        "mean_profit_factor": 1.8035220579396563,
        "mean_max_drawdown_r": 52.333333333333336,
        "mean_trade_count": 1370.0,
        "mean_confidence_ge_threshold_ratio": 0.3178523745946977
      },
      "summary_tuple": [
        0.32529780467738656,
        1.8035220579396563,
        -52.333333333333336,
        0.30735529108638393,
        0.4402053240203111,
        0.3178523745946977,
        1370.0
      ]
    },
    {
      "label_params": {
        "future_horizon": 24,
        "tp_mult": 2.2,
        "sl_mult": 1.5,
        "min_move_atr": 0.65,
        "neutral_margin_atr": 0.1
      },
      "label_config_hash": "796ab51293ddd45ee9e8cf07293fbe602c2604e2f7508c1d3554997a3c45913e",
      "feature_contract_hash": "3e4b29a628e09d925011eb052358fd32a1a863a863946297b6669730a8e88bce",
      "class_histogram": {
        "0": 19424,
        "1": 1036,
        "2": 14493
      },
      "summary": {
        "mean_accuracy": 0.38527560556933055,
        "mean_macro_f1": 0.29901072433637454,
        "mean_weighted_f1": 0.41395576270797524,
        "mean_expectancy_r": 0.20266984469628824,
        "mean_profit_factor": 1.4562188601075035,
        "mean_max_drawdown_r": 57.16666666666714,
        "mean_trade_count": 1563.0,
        "mean_confidence_ge_threshold_ratio": 0.37907686439061605
      },
      "summary_tuple": [
        0.20266984469628824,
        1.4562188601075035,
        -57.16666666666714,
        0.29901072433637454,
        0.41395576270797524,
        0.37907686439061605,
        1563.0
      ]
    },
    {
      "label_params": {
        "future_horizon": 30,
        "tp_mult": 2.4,
        "sl_mult": 1.6,
        "min_move_atr": 0.75,
        "neutral_margin_atr": 0.12
      },
      "label_config_hash": "49b283ba89aa4a2a54275bae4b1500d8b22460161e8c9f389fb4d7ccb433cd28",
      "feature_contract_hash": "3e4b29a628e09d925011eb052358fd32a1a863a863946297b6669730a8e88bce",
      "class_histogram": {
        "0": 19612,
        "1": 1070,
        "2": 14265
      },
      "summary": {
        "mean_accuracy": 0.4133918351774132,
        "mean_macro_f1": 0.3022022623531483,
        "mean_weighted_f1": 0.4233094314897773,
        "mean_expectancy_r": 0.2445233549425464,
        "mean_profit_factor": 1.5492255492255493,
        "mean_max_drawdown_r": 62.999999999999105,
        "mean_trade_count": 1513.0,
        "mean_confidence_ge_threshold_ratio": 0.3494849294162533
      },
      "summary_tuple": [
        0.2445233549425464,
        1.5492255492255493,
        -62.999999999999105,
        0.3022022623531483,
        0.4233094314897773,
        0.3494849294162533,
        1513.0
      ]
    }
  ],
  "selected_walk_forward_summary": {
    "mean_accuracy": 0.48026315789473684,
    "mean_macro_f1": 0.32936512173825105,
    "mean_weighted_f1": 0.48139526025557344,
    "mean_expectancy_r": 0.5505351622372899,
    "mean_profit_factor": 2.799741100323625,
    "mean_max_drawdown_r": 13.166666666666664,
    "mean_trade_count": 232.0,
    "mean_confidence_ge_threshold_ratio": 0.048436308161708616
  },
  "final_training_report": {
    "run_id": "20260525T130524Z_seq24_3e4b29a6_f87e9956",
    "run_dir": "C:\\Users\\dilla\\AppData\\Roaming\\MetaQuotes\\Terminal\\D0E8209F77C8CF37AD8BF550E51FF075\\MQL5\\Experts\\LSTM\\training_runs\\20260525T130524Z_seq24_3e4b29a6_f87e9956",
    "history_dir": "C:\\Users\\dilla\\AppData\\Roaming\\MetaQuotes\\Terminal\\D0E8209F77C8CF37AD8BF550E51FF075\\MQL5\\Experts\\LSTM\\training_runs",
    "index_path": "C:\\Users\\dilla\\AppData\\Roaming\\MetaQuotes\\Terminal\\D0E8209F77C8CF37AD8BF550E51FF075\\MQL5\\Experts\\LSTM\\training_runs\\index.jsonl",
    "latest_pointer_path": "C:\\Users\\dilla\\AppData\\Roaming\\MetaQuotes\\Terminal\\D0E8209F77C8CF37AD8BF550E51FF075\\MQL5\\Experts\\LSTM\\training_runs\\latest_run.json",
    "best_registry_path": "C:\\Users\\dilla\\AppData\\Roaming\\MetaQuotes\\Terminal\\D0E8209F77C8CF37AD8BF550E51FF075\\MQL5\\Experts\\LSTM\\training_runs\\best_registry.json",
    "resume_source": "history_best_checkpoint",
    "resumed_from_checkpoint": true,
    "checkpoint_dir": "C:\\Users\\dilla\\AppData\\Roaming\\MetaQuotes\\Terminal\\D0E8209F77C8CF37AD8BF550E51FF075\\MQL5\\Experts\\LSTM\\training_runs\\20260525T130524Z_seq24_3e4b29a6_f87e9956",
    "checkpoint_path": "C:\\Users\\dilla\\AppData\\Roaming\\MetaQuotes\\Terminal\\D0E8209F77C8CF37AD8BF550E51FF075\\MQL5\\Experts\\LSTM\\training_runs\\20260525T130524Z_seq24_3e4b29a6_f87e9956\\last.keras",
    "resume_checkpoint_path": "C:\\Users\\dilla\\AppData\\Roaming\\MetaQuotes\\Terminal\\D0E8209F77C8CF37AD8BF550E51FF075\\MQL5\\Experts\\LSTM\\training_runs\\20260525T111911Z_seq24_3e4b29a6_f66ad463\\best.keras",
    "best_checkpoint_path": "C:\\Users\\dilla\\AppData\\Roaming\\MetaQuotes\\Terminal\\D0E8209F77C8CF37AD8BF550E51FF075\\MQL5\\Experts\\LSTM\\training_runs\\20260525T130524Z_seq24_3e4b29a6_f87e9956\\best.keras",
    "state_path": "C:\\Users\\dilla\\AppData\\Roaming\\MetaQuotes\\Terminal\\D0E8209F77C8CF37AD8BF550E51FF075\\MQL5\\Experts\\LSTM\\training_runs\\20260525T130524Z_seq24_3e4b29a6_f87e9956\\training_state.json",
    "feature_contract": {
      "feature_count": 25,
      "sequence_length": 24,
      "feature_columns": [
        "Open",
        "High",
        "Low",
        "Close",
        "Volume",
        "RSI",
        "ATR",
        "MACD_Main",
        "MACD_Signal",
        "Bands_Upper",
        "Bands_Lower",
        "Stoch_Main",
        "Stoch_Signal",
        "ADX_Main",
        "ADX_PlusDI",
        "ADX_MinusDI",
        "RSI_H4",
        "MA_H4",
        "RSI_M15",
        "ATR_M15",
        "Hour_Sin",
        "Hour_Cos",
        "DayOfWeek_Sin",
        "DayOfWeek_Cos",
        "Daily_Trend_Proxy"
      ]
    },
    "feature_contract_hash": "3e4b29a628e09d925011eb052358fd32a1a863a863946297b6669730a8e88bce",
    "training_schema_version": 3,
    "model_family": "single_head_binary_booster_v1",
    "label_config": {
      "future_horizon": 18,
      "tp_mult": 1.8,
      "sl_mult": 1.2,
      "min_move_atr": 0.35,
      "neutral_margin_atr": 0.05
    },
    "label_config_hash": "f87e9956c3c96d7a38254acf479423f05552a5b7fd76dbb6d78fa442ec4d46c3",
    "class_histogram": {
      "0": 19630,
      "1": 945,
      "2": 14384
    },
    "best_validation_epoch": 16,
    "best_validation_score_tuple": [
      0.1251141552511415,
      1.2416225749559084,
      -35.00000000000004,
      0.784655681526918,
      0.9546888488563503,
      0.06960335621662853
    ],
    "best_validation_loss": 1.0267084836959839,
    "best_validation_metrics": {
      "accuracy": 0.9487032799389779,
      "macro_f1": 0.784655681526918,
      "weighted_f1": 0.9546888488563503,
      "macro_precision": 0.733326328371734,
      "macro_recall": 0.8761738085702844,
      "confusion_matrix": [
        [
          4776,
          218
        ],
        [
          51,
          199
        ]
      ],
      "classification_report": {
        "SKIP": {
          "precision": 0.9894344313238036,
          "recall": 0.9563476171405687,
          "f1-score": 0.9726097138784238,
          "support": 4994.0
        },
        "ENTER": {
          "precision": 0.47721822541966424,
          "recall": 0.796,
          "f1-score": 0.5967016491754122,
          "support": 250.0
        },
        "accuracy": 0.9487032799389779,
        "macro avg": {
          "precision": 0.733326328371734,
          "recall": 0.8761738085702844,
          "f1-score": 0.784655681526918,
          "support": 5244.0
        },
        "weighted avg": {
          "precision": 0.9650152758173133,
          "recall": 0.9487032799389779,
          "f1-score": 0.9546888488563503,
          "support": 5244.0
        }
      },
      "confidence_ge_threshold_ratio": 0.06960335621662853,
      "trading_proxy": {
        "trade_count": 365,
        "win_rate": 0.4821917808219178,
        "expectancy_r": 0.1251141552511415,
        "profit_factor": 1.2416225749559084,
        "max_drawdown_r": 35.00000000000004,
        "equity_curve_tail_r": [
          67.66666666666669,
          69.00000000000001,
          70.33333333333334,
          71.66666666666667,
          70.66666666666667,
          69.66666666666667,
          68.66666666666667,
          67.66666666666667,
          66.66666666666667,
          65.66666666666667,
          64.66666666666667,
          63.66666666666667,
          65.0,
          66.33333333333333,
          65.33333333333333,
          64.33333333333333,
          65.66666666666666,
          66.99999999999999,
          68.33333333333331,
          69.66666666666664,
          68.66666666666664,
          67.66666666666664,
          66.66666666666664,
          65.66666666666664,
          64.66666666666664,
          63.66666666666664,
          64.99999999999997,
          66.3333333333333,
          65.3333333333333,
          64.3333333333333,
          63.3333333333333,
          62.3333333333333,
          61.3333333333333,
          62.666666666666636,
          61.666666666666636,
          60.666666666666636,
          59.666666666666636,
          58.666666666666636,
          57.666666666666636,
          56.666666666666636,
          55.666666666666636,
          54.666666666666636,
          53.666666666666636,
          52.666666666666636,
          51.666666666666636,
          52.99999999999997,
          54.33333333333331,
          53.33333333333331,
          52.33333333333331,
          51.33333333333331,
          50.33333333333331,
          49.33333333333331,
          48.33333333333331,
          49.66666666666664,
          50.99999999999998,
          52.333333333333314,
          51.333333333333314,
          50.333333333333314,
          49.333333333333314,
          48.333333333333314,
          47.333333333333314,
          46.333333333333314,
          45.333333333333314,
          44.333333333333314,
          43.333333333333314,
          42.333333333333314,
          41.333333333333314,
          40.333333333333314,
          39.333333333333314,
          40.66666666666665,
          41.999999999999986,
          43.33333333333332,
          44.66666666666666,
          45.99999999999999,
          47.33333333333333,
          48.666666666666664,
          47.666666666666664,
          46.666666666666664,
          48.0,
          47.0,
          48.333333333333336,
          49.66666666666667,
          51.00000000000001,
          50.00000000000001,
          49.00000000000001,
          50.33333333333334,
          51.66666666666668,
          53.000000000000014,
          54.33333333333335,
          53.33333333333335,
          52.33333333333335,
          51.33333333333335,
          50.33333333333335,
          49.33333333333335,
          48.33333333333335,
          47.33333333333335,
          46.33333333333335,
          45.33333333333335,
          44.33333333333335,
          45.666666666666686
        ]
      }
    },
    "training_history": {
      "epochs_ran": 76,
      "final_loss": 0.6479492783546448,
      "final_val_loss": 1.0607686042785645,
      "final_accuracy": 0.6119106411933899,
      "final_val_accuracy": 0.4696796238422394,
      "start_epoch": 0,
      "target_epochs": 300
    },
    "validation_metrics": {
      "accuracy": 0.9487032799389779,
      "macro_f1": 0.784655681526918,
      "weighted_f1": 0.9546888488563503,
      "macro_precision": 0.733326328371734,
      "macro_recall": 0.8761738085702844,
      "confusion_matrix": [
        [
          4776,
          218
        ],
        [
          51,
          199
        ]
      ],
      "classification_report": {
        "SKIP": {
          "precision": 0.9894344313238036,
          "recall": 0.9563476171405687,
          "f1-score": 0.9726097138784238,
          "support": 4994.0
        },
        "ENTER": {
          "precision": 0.47721822541966424,
          "recall": 0.796,
          "f1-score": 0.5967016491754122,
          "support": 250.0
        },
        "accuracy": 0.9487032799389779,
        "macro avg": {
          "precision": 0.733326328371734,
          "recall": 0.8761738085702844,
          "f1-score": 0.784655681526918,
          "support": 5244.0
        },
        "weighted avg": {
          "precision": 0.9650152758173133,
          "recall": 0.9487032799389779,
          "f1-score": 0.9546888488563503,
          "support": 5244.0
        }
      },
      "confidence_ge_threshold_ratio": 0.06960335621662853,
      "trading_proxy": {
        "trade_count": 365,
        "win_rate": 0.4821917808219178,
        "expectancy_r": 0.1251141552511415,
        "profit_factor": 1.2416225749559084,
        "max_drawdown_r": 35.00000000000004,
        "equity_curve_tail_r": [
          67.66666666666669,
          69.00000000000001,
          70.33333333333334,
          71.66666666666667,
          70.66666666666667,
          69.66666666666667,
          68.66666666666667,
          67.66666666666667,
          66.66666666666667,
          65.66666666666667,
          64.66666666666667,
          63.66666666666667,
          65.0,
          66.33333333333333,
          65.33333333333333,
          64.33333333333333,
          65.66666666666666,
          66.99999999999999,
          68.33333333333331,
          69.66666666666664,
          68.66666666666664,
          67.66666666666664,
          66.66666666666664,
          65.66666666666664,
          64.66666666666664,
          63.66666666666664,
          64.99999999999997,
          66.3333333333333,
          65.3333333333333,
          64.3333333333333,
          63.3333333333333,
          62.3333333333333,
          61.3333333333333,
          62.666666666666636,
          61.666666666666636,
          60.666666666666636,
          59.666666666666636,
          58.666666666666636,
          57.666666666666636,
          56.666666666666636,
          55.666666666666636,
          54.666666666666636,
          53.666666666666636,
          52.666666666666636,
          51.666666666666636,
          52.99999999999997,
          54.33333333333331,
          53.33333333333331,
          52.33333333333331,
          51.33333333333331,
          50.33333333333331,
          49.33333333333331,
          48.33333333333331,
          49.66666666666664,
          50.99999999999998,
          52.333333333333314,
          51.333333333333314,
          50.333333333333314,
          49.333333333333314,
          48.333333333333314,
          47.333333333333314,
          46.333333333333314,
          45.333333333333314,
          44.333333333333314,
          43.333333333333314,
          42.333333333333314,
          41.333333333333314,
          40.333333333333314,
          39.333333333333314,
          40.66666666666665,
          41.999999999999986,
          43.33333333333332,
          44.66666666666666,
          45.99999999999999,
          47.33333333333333,
          48.666666666666664,
          47.666666666666664,
          46.666666666666664,
          48.0,
          47.0,
          48.333333333333336,
          49.66666666666667,
          51.00000000000001,
          50.00000000000001,
          49.00000000000001,
          50.33333333333334,
          51.66666666666668,
          53.000000000000014,
          54.33333333333335,
          53.33333333333335,
          52.33333333333335,
          51.33333333333335,
          50.33333333333335,
          49.33333333333335,
          48.33333333333335,
          47.33333333333335,
          46.33333333333335,
          45.33333333333335,
          44.33333333333335,
          45.666666666666686
        ]
      }
    },
    "test_metrics": {
      "accuracy": 0.9699656750572082,
      "macro_f1": 0.8542634144714667,
      "weighted_f1": 0.9733457410967918,
      "macro_precision": 0.7912992617240304,
      "macro_recall": 0.9612395682194713,
      "confusion_matrix": [
        [
          3253,
          98
        ],
        [
          7,
          138
        ]
      ],
      "classification_report": {
        "SKIP": {
          "precision": 0.9978527607361963,
          "recall": 0.9707549985079081,
          "f1-score": 0.9841173801240357,
          "support": 3351.0
        },
        "ENTER": {
          "precision": 0.5847457627118644,
          "recall": 0.9517241379310345,
          "f1-score": 0.7244094488188977,
          "support": 145.0
        },
        "accuracy": 0.9699656750572082,
        "macro avg": {
          "precision": 0.7912992617240304,
          "recall": 0.9612395682194713,
          "f1-score": 0.8542634144714667,
          "support": 3496.0
        },
        "weighted avg": {
          "precision": 0.9807187462300384,
          "recall": 0.9699656750572082,
          "f1-score": 0.9733457410967918,
          "support": 3496.0
        }
      },
      "confidence_ge_threshold_ratio": 0.06292906178489703,
      "trading_proxy": {
        "trade_count": 220,
        "win_rate": 0.5863636363636363,
        "expectancy_r": 0.3681818181818181,
        "profit_factor": 1.89010989010989,
        "max_drawdown_r": 23.333333333333442,
        "equity_curve_tail_r": [
          84.33333333333331,
          83.33333333333331,
          82.33333333333331,
          81.33333333333331,
          82.66666666666664,
          83.99999999999997,
          85.3333333333333,
          86.66666666666663,
          87.99999999999996,
          89.33333333333329,
          90.66666666666661,
          89.66666666666661,
          90.99999999999994,
          92.33333333333327,
          93.6666666666666,
          94.99999999999993,
          93.99999999999993,
          92.99999999999993,
          91.99999999999993,
          93.33333333333326,
          92.33333333333326,
          91.33333333333326,
          90.33333333333326,
          89.33333333333326,
          88.33333333333326,
          87.33333333333326,
          86.33333333333326,
          85.33333333333326,
          84.33333333333326,
          83.33333333333326,
          82.33333333333326,
          81.33333333333326,
          80.33333333333326,
          79.33333333333326,
          80.66666666666659,
          81.99999999999991,
          83.33333333333324,
          82.33333333333324,
          81.33333333333324,
          82.66666666666657,
          83.9999999999999,
          85.33333333333323,
          86.66666666666656,
          87.99999999999989,
          89.33333333333321,
          90.66666666666654,
          91.99999999999987,
          93.3333333333332,
          94.66666666666653,
          93.66666666666653,
          92.66666666666653,
          91.66666666666653,
          90.66666666666653,
          89.66666666666653,
          88.66666666666653,
          87.66666666666653,
          86.66666666666653,
          85.66666666666653,
          84.66666666666653,
          83.66666666666653,
          82.66666666666653,
          83.99999999999986,
          85.33333333333319,
          86.66666666666652,
          85.66666666666652,
          84.66666666666652,
          83.66666666666652,
          82.66666666666652,
          83.99999999999984,
          82.99999999999984,
          81.99999999999984,
          80.99999999999984,
          79.99999999999984,
          78.99999999999984,
          80.33333333333317,
          81.6666666666665,
          82.99999999999983,
          81.99999999999983,
          80.99999999999983,
          79.99999999999983,
          81.33333333333316,
          82.66666666666649,
          81.66666666666649,
          80.66666666666649,
          79.66666666666649,
          78.66666666666649,
          77.66666666666649,
          76.66666666666649,
          75.66666666666649,
          74.66666666666649,
          73.66666666666649,
          72.66666666666649,
          71.66666666666649,
          72.99999999999982,
          74.33333333333314,
          75.66666666666647,
          76.9999999999998,
          78.33333333333313,
          79.66666666666646,
          80.99999999999979
        ]
      }
    },
    "final_sample_weights": 1.0000001192092896,
    "comparison_to_previous": {
      "previous_run_id": "20260525T111911Z_seq24_3e4b29a6_f66ad463",
      "previous_run_dir": "C:\\Users\\dilla\\AppData\\Roaming\\MetaQuotes\\Terminal\\D0E8209F77C8CF37AD8BF550E51FF075\\MQL5\\Experts\\LSTM\\training_runs\\20260525T111911Z_seq24_3e4b29a6_f66ad463",
      "previous_best_score_tuple": [
        0.5720430107526882,
        2.8472222222222228,
        -11.666666666666668,
        0.34021439028334227,
        0.487123311316716,
        0.059126454320045777
      ],
      "current_best_score_tuple": [
        0.5377777777777778,
        2.6133333333333333,
        -9.0,
        0.3270441354753808,
        0.45102650020935825,
        0.05415713196033562
      ],
      "new_best_model": false,
      "metric_deltas": {
        "validation_accuracy_delta": -0.06473660060059011,
        "test_accuracy_delta": -0.05005720823798626,
        "validation_macro_f1_delta": -0.013170254807961468,
        "test_macro_f1_delta": -0.022766114125839176,
        "validation_weighted_f1_delta": -0.03609681110735774,
        "test_weighted_f1_delta": -0.03965797803525184,
        "validation_macro_precision_delta": 0.0016126212020463604,
        "test_macro_precision_delta": -0.00701185804559834,
        "validation_macro_recall_delta": 0.06000098386233926,
        "test_macro_recall_delta": 0.01840904666212373,
        "validation_confidence_ge_threshold_ratio_delta": -0.004969322359710156,
        "test_confidence_ge_threshold_ratio_delta": -0.016018306636155603,
        "validation_trading_expectancy_r_delta": -0.034265232974910353,
        "test_trading_expectancy_r_delta": -0.7753774680603948,
        "validation_trading_profit_factor_delta": -0.23388888888888948,
        "test_trading_profit_factor_delta": -1.6367521367521372,
        "validation_trading_max_drawdown_r_delta": -2.666666666666668,
        "test_trading_max_drawdown_r_delta": -1.6666666666666643,
        "validation_trading_trade_count_delta": -235.0,
        "test_trading_trade_count_delta": -170.0,
        "validation_trading_win_rate_delta": -0.007956989247311808,
        "test_trading_win_rate_delta": -0.3526132404181185
      }
    },
    "aux_horizons": [],
    "selection_reason": "selected by best walk-forward expectancy/profit factor with macro F1 tie-breaker, subject to coverage floor; training resumes from best compatible history when available",
    "base_validation_metrics": {
      "accuracy": 0.4139969488939741,
      "macro_f1": 0.3270441354753808,
      "weighted_f1": 0.45102650020935825,
      "macro_precision": 0.35521739107479416,
      "macro_recall": 0.41629959884048473,
      "confusion_matrix": [
        [
          1370,
          657,
          858
        ],
        [
          27,
          51,
          38
        ],
        [
          1020,
          473,
          750
        ]
      ],
      "classification_report": {
        "DOWN": {
          "precision": 0.5668183698800165,
          "recall": 0.4748700173310225,
          "f1-score": 0.5167861184458695,
          "support": 2885.0
        },
        "SIDEWAYS": {
          "precision": 0.04318374259102455,
          "recall": 0.4396551724137931,
          "f1-score": 0.07864302235929067,
          "support": 116.0
        },
        "UP": {
          "precision": 0.4556500607533414,
          "recall": 0.3343736067766384,
          "f1-score": 0.3857032656209823,
          "support": 2243.0
        },
        "accuracy": 0.4139969488939741,
        "macro avg": {
          "precision": 0.35521739107479416,
          "recall": 0.41629959884048473,
          "f1-score": 0.3270441354753808,
          "support": 5244.0
        },
        "weighted avg": {
          "precision": 0.5076856211888161,
          "recall": 0.4139969488939741,
          "f1-score": 0.45102650020935825,
          "support": 5244.0
        }
      },
      "confidence_ge_threshold_ratio": 0.05415713196033562,
      "trading_proxy": {
        "trade_count": 75,
        "win_rate": 0.6533333333333333,
        "expectancy_r": 0.5377777777777778,
        "profit_factor": 2.6133333333333333,
        "max_drawdown_r": 9.0,
        "equity_curve_tail_r": [
          1.3333333333333333,
          0.33333333333333326,
          1.6666666666666665,
          3.0,
          4.333333333333333,
          5.666666666666666,
          6.999999999999999,
          8.333333333333332,
          9.666666666666666,
          8.666666666666666,
          7.666666666666666,
          6.666666666666666,
          7.999999999999999,
          6.999999999999999,
          6.999999999999999,
          8.333333333333332,
          9.666666666666666,
          8.666666666666666,
          7.666666666666666,
          6.666666666666666,
          5.666666666666666,
          4.666666666666666,
          5.999999999999999,
          7.333333333333332,
          8.666666666666666,
          10.0,
          11.333333333333334,
          12.666666666666668,
          14.000000000000002,
          13.000000000000002,
          14.333333333333336,
          15.66666666666667,
          17.000000000000004,
          18.333333333333336,
          19.666666666666668,
          21.0,
          22.333333333333332,
          23.666666666666664,
          24.999999999999996,
          26.33333333333333,
          27.66666666666666,
          28.999999999999993,
          30.333333333333325,
          31.666666666666657,
          30.666666666666657,
          29.666666666666657,
          30.99999999999999,
          32.33333333333332,
          33.66666666666666,
          34.99999999999999,
          36.33333333333333,
          37.666666666666664,
          39.0,
          40.333333333333336,
          41.66666666666667,
          43.00000000000001,
          44.33333333333334,
          45.66666666666668,
          44.66666666666668,
          43.66666666666668,
          42.66666666666668,
          41.66666666666668,
          40.66666666666668,
          39.66666666666668,
          38.66666666666668,
          37.66666666666668,
          36.66666666666668,
          38.000000000000014,
          37.000000000000014,
          38.33333333333335,
          39.666666666666686,
          41.00000000000002,
          40.00000000000002,
          39.00000000000002,
          40.33333333333336
        ]
      }
    },
    "base_test_metrics": {
      "accuracy": 0.3790045766590389,
      "macro_f1": 0.285727220875645,
      "weighted_f1": 0.4149193904873423,
      "macro_precision": 0.32208686015624227,
      "macro_recall": 0.3527991859340072,
      "confusion_matrix": [
        [
          1017,
          553,
          490
        ],
        [
          43,
          35,
          19
        ],
        [
          691,
          375,
          273
        ]
      ],
      "classification_report": {
        "DOWN": {
          "precision": 0.5808109651627641,
          "recall": 0.4936893203883495,
          "f1-score": 0.533718184203621,
          "support": 2060.0
        },
        "SIDEWAYS": {
          "precision": 0.036344755970924195,
          "recall": 0.36082474226804123,
          "f1-score": 0.0660377358490566,
          "support": 97.0
        },
        "UP": {
          "precision": 0.3491048593350384,
          "recall": 0.20388349514563106,
          "f1-score": 0.25742574257425743,
          "support": 1339.0
        },
        "accuracy": 0.3790045766590389,
        "macro avg": {
          "precision": 0.32208686015624227,
          "recall": 0.3527991859340072,
          "f1-score": 0.285727220875645,
          "support": 3496.0
        },
        "weighted avg": {
          "precision": 0.4769586488026573,
          "recall": 0.3790045766590389,
          "f1-score": 0.4149193904873423,
          "support": 3496.0
        }
      },
      "confidence_ge_threshold_ratio": 0.04891304347826087,
      "trading_proxy": {
        "trade_count": 35,
        "win_rate": 0.2571428571428571,
        "expectancy_r": -0.34285714285714286,
        "profit_factor": 0.5,
        "max_drawdown_r": 21.333333333333336,
        "equity_curve_tail_r": [
          1.3333333333333333,
          2.6666666666666665,
          4.0,
          5.333333333333333,
          6.666666666666666,
          7.999999999999999,
          9.333333333333332,
          8.333333333333332,
          7.333333333333332,
          6.333333333333332,
          5.333333333333332,
          4.333333333333332,
          3.333333333333332,
          4.666666666666665,
          3.666666666666665,
          2.666666666666665,
          1.6666666666666652,
          0.6666666666666652,
          -0.3333333333333348,
          -1.3333333333333348,
          -1.3333333333333348,
          -1.5543122344752192e-15,
          -1.5543122344752192e-15,
          -1.0000000000000016,
          -2.0000000000000018,
          -3.0000000000000018,
          -4.000000000000002,
          -5.000000000000002,
          -6.000000000000002,
          -7.000000000000002,
          -8.000000000000002,
          -9.000000000000002,
          -10.000000000000002,
          -11.000000000000002,
          -12.000000000000002
        ]
      }
    },
    "booster": {
      "feature_count": 30,
      "feature_columns": [
        "base_prob_down",
        "base_prob_sideways",
        "base_prob_up",
        "base_confidence",
        "base_confidence_gap",
        "last_Open",
        "last_High",
        "last_Low",
        "last_Close",
        "last_Volume",
        "last_RSI",
        "last_ATR",
        "last_MACD_Main",
        "last_MACD_Signal",
        "last_Bands_Upper",
        "last_Bands_Lower",
        "last_Stoch_Main",
        "last_Stoch_Signal",
        "last_ADX_Main",
        "last_ADX_PlusDI",
        "last_ADX_MinusDI",
        "last_RSI_H4",
        "last_MA_H4",
        "last_RSI_M15",
        "last_ATR_M15",
        "last_Hour_Sin",
        "last_Hour_Cos",
        "last_DayOfWeek_Sin",
        "last_DayOfWeek_Cos",
        "last_Daily_Trend_Proxy"
      ],
      "params": {
        "n_estimators": 170,
        "learning_rate": 0.03,
        "max_depth": 3,
        "min_samples_leaf": 20,
        "subsample": 0.8
      },
      "validation_metrics": {
        "accuracy": 0.8976803304734668,
        "macro_f1": 0.7982984628760603,
        "weighted_f1": 0.9097375240072398,
        "macro_precision": 0.7500831143027004,
        "macro_recall": 0.9072477229782807,
        "confusion_matrix": [
          [
            2517,
            295
          ],
          [
            27,
            308
          ]
        ],
        "classification_report": {
          "SKIP": {
            "precision": 0.9893867924528302,
            "recall": 0.8950924608819346,
            "f1-score": 0.9398805078416729,
            "support": 2812.0
          },
          "ENTER": {
            "precision": 0.5107794361525705,
            "recall": 0.9194029850746268,
            "f1-score": 0.6567164179104478,
            "support": 335.0
          },
          "accuracy": 0.8976803304734668,
          "macro avg": {
            "precision": 0.7500831143027004,
            "recall": 0.9072477229782807,
            "f1-score": 0.7982984628760603,
            "support": 3147.0
          },
          "weighted avg": {
            "precision": 0.9384387580198507,
            "recall": 0.8976803304734668,
            "f1-score": 0.9097375240072398,
            "support": 3147.0
          }
        },
        "confidence_ge_threshold_ratio": 0.1754051477597712,
        "trading_proxy": {
          "trade_count": 552,
          "win_rate": 0.5253623188405797,
          "expectancy_r": 0.22584541062801927,
          "profit_factor": 1.475826972010178,
          "max_drawdown_r": 33.33333333333332,
          "equity_curve_tail_r": [
            130.33333333333326,
            129.33333333333326,
            128.33333333333326,
            127.33333333333326,
            126.33333333333326,
            125.33333333333326,
            124.33333333333326,
            123.33333333333326,
            122.33333333333326,
            121.33333333333326,
            120.33333333333326,
            119.33333333333326,
            118.33333333333326,
            117.33333333333326,
            116.33333333333326,
            115.33333333333326,
            114.33333333333326,
            113.33333333333326,
            112.33333333333326,
            111.33333333333326,
            110.33333333333326,
            109.33333333333326,
            108.33333333333326,
            109.66666666666659,
            110.99999999999991,
            112.33333333333324,
            111.33333333333324,
            112.66666666666657,
            113.9999999999999,
            115.33333333333323,
            116.66666666666656,
            115.66666666666656,
            114.66666666666656,
            113.66666666666656,
            114.99999999999989,
            116.33333333333321,
            115.33333333333321,
            114.33333333333321,
            115.66666666666654,
            116.99999999999987,
            115.99999999999987,
            114.99999999999987,
            113.99999999999987,
            112.99999999999987,
            114.3333333333332,
            115.66666666666653,
            116.99999999999986,
            118.33333333333319,
            119.66666666666652,
            120.99999999999984,
            122.33333333333317,
            121.33333333333317,
            120.33333333333317,
            119.33333333333317,
            118.33333333333317,
            117.33333333333317,
            116.33333333333317,
            115.33333333333317,
            114.33333333333317,
            115.6666666666665,
            116.99999999999983,
            118.33333333333316,
            119.66666666666649,
            120.99999999999982,
            122.33333333333314,
            123.66666666666647,
            124.9999999999998,
            126.33333333333313,
            127.66666666666646,
            128.9999999999998,
            127.9999999999998,
            129.33333333333314,
            130.6666666666665,
            131.99999999999983,
            133.33333333333317,
            132.33333333333317,
            131.33333333333317,
            130.33333333333317,
            131.66666666666652,
            132.99999999999986,
            134.3333333333332,
            133.3333333333332,
            132.3333333333332,
            131.3333333333332,
            130.3333333333332,
            129.3333333333332,
            128.3333333333332,
            127.3333333333332,
            126.3333333333332,
            127.66666666666653,
            126.66666666666653,
            125.66666666666653,
            126.99999999999986,
            128.3333333333332,
            127.3333333333332,
            126.3333333333332,
            125.3333333333332,
            124.3333333333332,
            123.3333333333332,
            124.66666666666653
          ]
        },
        "tuned_confidence_threshold": 0.67,
        "tuned_min_confidence_edge": 0.0
      },
      "validation_tuple": [
        0.22584541062801927,
        1.475826972010178,
        -33.33333333333332,
        0.7982984628760603,
        0.9097375240072398,
        0.1754051477597712
      ],
      "train_rows": 7341,
      "val_rows": 3147,
      "onnx_path": "C:\\Users\\dilla\\AppData\\Roaming\\MetaQuotes\\Terminal\\D0E8209F77C8CF37AD8BF550E51FF075\\MQL5\\Experts\\LSTM\\booster_eurusd_H1.onnx"
    },
    "final_stack_metrics": {
      "base_validation_metrics": {
        "accuracy": 0.4139969488939741,
        "macro_f1": 0.3270441354753808,
        "weighted_f1": 0.45102650020935825,
        "macro_precision": 0.35521739107479416,
        "macro_recall": 0.41629959884048473,
        "confusion_matrix": [
          [
            1370,
            657,
            858
          ],
          [
            27,
            51,
            38
          ],
          [
            1020,
            473,
            750
          ]
        ],
        "classification_report": {
          "DOWN": {
            "precision": 0.5668183698800165,
            "recall": 0.4748700173310225,
            "f1-score": 0.5167861184458695,
            "support": 2885.0
          },
          "SIDEWAYS": {
            "precision": 0.04318374259102455,
            "recall": 0.4396551724137931,
            "f1-score": 0.07864302235929067,
            "support": 116.0
          },
          "UP": {
            "precision": 0.4556500607533414,
            "recall": 0.3343736067766384,
            "f1-score": 0.3857032656209823,
            "support": 2243.0
          },
          "accuracy": 0.4139969488939741,
          "macro avg": {
            "precision": 0.35521739107479416,
            "recall": 0.41629959884048473,
            "f1-score": 0.3270441354753808,
            "support": 5244.0
          },
          "weighted avg": {
            "precision": 0.5076856211888161,
            "recall": 0.4139969488939741,
            "f1-score": 0.45102650020935825,
            "support": 5244.0
          }
        },
        "confidence_ge_threshold_ratio": 0.05415713196033562,
        "trading_proxy": {
          "trade_count": 75,
          "win_rate": 0.6533333333333333,
          "expectancy_r": 0.5377777777777778,
          "profit_factor": 2.6133333333333333,
          "max_drawdown_r": 9.0,
          "equity_curve_tail_r": [
            1.3333333333333333,
            0.33333333333333326,
            1.6666666666666665,
            3.0,
            4.333333333333333,
            5.666666666666666,
            6.999999999999999,
            8.333333333333332,
            9.666666666666666,
            8.666666666666666,
            7.666666666666666,
            6.666666666666666,
            7.999999999999999,
            6.999999999999999,
            6.999999999999999,
            8.333333333333332,
            9.666666666666666,
            8.666666666666666,
            7.666666666666666,
            6.666666666666666,
            5.666666666666666,
            4.666666666666666,
            5.999999999999999,
            7.333333333333332,
            8.666666666666666,
            10.0,
            11.333333333333334,
            12.666666666666668,
            14.000000000000002,
            13.000000000000002,
            14.333333333333336,
            15.66666666666667,
            17.000000000000004,
            18.333333333333336,
            19.666666666666668,
            21.0,
            22.333333333333332,
            23.666666666666664,
            24.999999999999996,
            26.33333333333333,
            27.66666666666666,
            28.999999999999993,
            30.333333333333325,
            31.666666666666657,
            30.666666666666657,
            29.666666666666657,
            30.99999999999999,
            32.33333333333332,
            33.66666666666666,
            34.99999999999999,
            36.33333333333333,
            37.666666666666664,
            39.0,
            40.333333333333336,
            41.66666666666667,
            43.00000000000001,
            44.33333333333334,
            45.66666666666668,
            44.66666666666668,
            43.66666666666668,
            42.66666666666668,
            41.66666666666668,
            40.66666666666668,
            39.66666666666668,
            38.66666666666668,
            37.66666666666668,
            36.66666666666668,
            38.000000000000014,
            37.000000000000014,
            38.33333333333335,
            39.666666666666686,
            41.00000000000002,
            40.00000000000002,
            39.00000000000002,
            40.33333333333336
          ]
        }
      },
      "base_test_metrics": {
        "accuracy": 0.3790045766590389,
        "macro_f1": 0.285727220875645,
        "weighted_f1": 0.4149193904873423,
        "macro_precision": 0.32208686015624227,
        "macro_recall": 0.3527991859340072,
        "confusion_matrix": [
          [
            1017,
            553,
            490
          ],
          [
            43,
            35,
            19
          ],
          [
            691,
            375,
            273
          ]
        ],
        "classification_report": {
          "DOWN": {
            "precision": 0.5808109651627641,
            "recall": 0.4936893203883495,
            "f1-score": 0.533718184203621,
            "support": 2060.0
          },
          "SIDEWAYS": {
            "precision": 0.036344755970924195,
            "recall": 0.36082474226804123,
            "f1-score": 0.0660377358490566,
            "support": 97.0
          },
          "UP": {
            "precision": 0.3491048593350384,
            "recall": 0.20388349514563106,
            "f1-score": 0.25742574257425743,
            "support": 1339.0
          },
          "accuracy": 0.3790045766590389,
          "macro avg": {
            "precision": 0.32208686015624227,
            "recall": 0.3527991859340072,
            "f1-score": 0.285727220875645,
            "support": 3496.0
          },
          "weighted avg": {
            "precision": 0.4769586488026573,
            "recall": 0.3790045766590389,
            "f1-score": 0.4149193904873423,
            "support": 3496.0
          }
        },
        "confidence_ge_threshold_ratio": 0.04891304347826087,
        "trading_proxy": {
          "trade_count": 35,
          "win_rate": 0.2571428571428571,
          "expectancy_r": -0.34285714285714286,
          "profit_factor": 0.5,
          "max_drawdown_r": 21.333333333333336,
          "equity_curve_tail_r": [
            1.3333333333333333,
            2.6666666666666665,
            4.0,
            5.333333333333333,
            6.666666666666666,
            7.999999999999999,
            9.333333333333332,
            8.333333333333332,
            7.333333333333332,
            6.333333333333332,
            5.333333333333332,
            4.333333333333332,
            3.333333333333332,
            4.666666666666665,
            3.666666666666665,
            2.666666666666665,
            1.6666666666666652,
            0.6666666666666652,
            -0.3333333333333348,
            -1.3333333333333348,
            -1.3333333333333348,
            -1.5543122344752192e-15,
            -1.5543122344752192e-15,
            -1.0000000000000016,
            -2.0000000000000018,
            -3.0000000000000018,
            -4.000000000000002,
            -5.000000000000002,
            -6.000000000000002,
            -7.000000000000002,
            -8.000000000000002,
            -9.000000000000002,
            -10.000000000000002,
            -11.000000000000002,
            -12.000000000000002
          ]
        }
      },
      "combined_validation_metrics": {
        "accuracy": 0.9487032799389779,
        "macro_f1": 0.784655681526918,
        "weighted_f1": 0.9546888488563503,
        "macro_precision": 0.733326328371734,
        "macro_recall": 0.8761738085702844,
        "confusion_matrix": [
          [
            4776,
            218
          ],
          [
            51,
            199
          ]
        ],
        "classification_report": {
          "SKIP": {
            "precision": 0.9894344313238036,
            "recall": 0.9563476171405687,
            "f1-score": 0.9726097138784238,
            "support": 4994.0
          },
          "ENTER": {
            "precision": 0.47721822541966424,
            "recall": 0.796,
            "f1-score": 0.5967016491754122,
            "support": 250.0
          },
          "accuracy": 0.9487032799389779,
          "macro avg": {
            "precision": 0.733326328371734,
            "recall": 0.8761738085702844,
            "f1-score": 0.784655681526918,
            "support": 5244.0
          },
          "weighted avg": {
            "precision": 0.9650152758173133,
            "recall": 0.9487032799389779,
            "f1-score": 0.9546888488563503,
            "support": 5244.0
          }
        },
        "confidence_ge_threshold_ratio": 0.06960335621662853,
        "trading_proxy": {
          "trade_count": 365,
          "win_rate": 0.4821917808219178,
          "expectancy_r": 0.1251141552511415,
          "profit_factor": 1.2416225749559084,
          "max_drawdown_r": 35.00000000000004,
          "equity_curve_tail_r": [
            67.66666666666669,
            69.00000000000001,
            70.33333333333334,
            71.66666666666667,
            70.66666666666667,
            69.66666666666667,
            68.66666666666667,
            67.66666666666667,
            66.66666666666667,
            65.66666666666667,
            64.66666666666667,
            63.66666666666667,
            65.0,
            66.33333333333333,
            65.33333333333333,
            64.33333333333333,
            65.66666666666666,
            66.99999999999999,
            68.33333333333331,
            69.66666666666664,
            68.66666666666664,
            67.66666666666664,
            66.66666666666664,
            65.66666666666664,
            64.66666666666664,
            63.66666666666664,
            64.99999999999997,
            66.3333333333333,
            65.3333333333333,
            64.3333333333333,
            63.3333333333333,
            62.3333333333333,
            61.3333333333333,
            62.666666666666636,
            61.666666666666636,
            60.666666666666636,
            59.666666666666636,
            58.666666666666636,
            57.666666666666636,
            56.666666666666636,
            55.666666666666636,
            54.666666666666636,
            53.666666666666636,
            52.666666666666636,
            51.666666666666636,
            52.99999999999997,
            54.33333333333331,
            53.33333333333331,
            52.33333333333331,
            51.33333333333331,
            50.33333333333331,
            49.33333333333331,
            48.33333333333331,
            49.66666666666664,
            50.99999999999998,
            52.333333333333314,
            51.333333333333314,
            50.333333333333314,
            49.333333333333314,
            48.333333333333314,
            47.333333333333314,
            46.333333333333314,
            45.333333333333314,
            44.333333333333314,
            43.333333333333314,
            42.333333333333314,
            41.333333333333314,
            40.333333333333314,
            39.333333333333314,
            40.66666666666665,
            41.999999999999986,
            43.33333333333332,
            44.66666666666666,
            45.99999999999999,
            47.33333333333333,
            48.666666666666664,
            47.666666666666664,
            46.666666666666664,
            48.0,
            47.0,
            48.333333333333336,
            49.66666666666667,
            51.00000000000001,
            50.00000000000001,
            49.00000000000001,
            50.33333333333334,
            51.66666666666668,
            53.000000000000014,
            54.33333333333335,
            53.33333333333335,
            52.33333333333335,
            51.33333333333335,
            50.33333333333335,
            49.33333333333335,
            48.33333333333335,
            47.33333333333335,
            46.33333333333335,
            45.33333333333335,
            44.33333333333335,
            45.666666666666686
          ]
        }
      },
      "combined_test_metrics": {
        "accuracy": 0.9699656750572082,
        "macro_f1": 0.8542634144714667,
        "weighted_f1": 0.9733457410967918,
        "macro_precision": 0.7912992617240304,
        "macro_recall": 0.9612395682194713,
        "confusion_matrix": [
          [
            3253,
            98
          ],
          [
            7,
            138
          ]
        ],
        "classification_report": {
          "SKIP": {
            "precision": 0.9978527607361963,
            "recall": 0.9707549985079081,
            "f1-score": 0.9841173801240357,
            "support": 3351.0
          },
          "ENTER": {
            "precision": 0.5847457627118644,
            "recall": 0.9517241379310345,
            "f1-score": 0.7244094488188977,
            "support": 145.0
          },
          "accuracy": 0.9699656750572082,
          "macro avg": {
            "precision": 0.7912992617240304,
            "recall": 0.9612395682194713,
            "f1-score": 0.8542634144714667,
            "support": 3496.0
          },
          "weighted avg": {
            "precision": 0.9807187462300384,
            "recall": 0.9699656750572082,
            "f1-score": 0.9733457410967918,
            "support": 3496.0
          }
        },
        "confidence_ge_threshold_ratio": 0.06292906178489703,
        "trading_proxy": {
          "trade_count": 220,
          "win_rate": 0.5863636363636363,
          "expectancy_r": 0.3681818181818181,
          "profit_factor": 1.89010989010989,
          "max_drawdown_r": 23.333333333333442,
          "equity_curve_tail_r": [
            84.33333333333331,
            83.33333333333331,
            82.33333333333331,
            81.33333333333331,
            82.66666666666664,
            83.99999999999997,
            85.3333333333333,
            86.66666666666663,
            87.99999999999996,
            89.33333333333329,
            90.66666666666661,
            89.66666666666661,
            90.99999999999994,
            92.33333333333327,
            93.6666666666666,
            94.99999999999993,
            93.99999999999993,
            92.99999999999993,
            91.99999999999993,
            93.33333333333326,
            92.33333333333326,
            91.33333333333326,
            90.33333333333326,
            89.33333333333326,
            88.33333333333326,
            87.33333333333326,
            86.33333333333326,
            85.33333333333326,
            84.33333333333326,
            83.33333333333326,
            82.33333333333326,
            81.33333333333326,
            80.33333333333326,
            79.33333333333326,
            80.66666666666659,
            81.99999999999991,
            83.33333333333324,
            82.33333333333324,
            81.33333333333324,
            82.66666666666657,
            83.9999999999999,
            85.33333333333323,
            86.66666666666656,
            87.99999999999989,
            89.33333333333321,
            90.66666666666654,
            91.99999999999987,
            93.3333333333332,
            94.66666666666653,
            93.66666666666653,
            92.66666666666653,
            91.66666666666653,
            90.66666666666653,
            89.66666666666653,
            88.66666666666653,
            87.66666666666653,
            86.66666666666653,
            85.66666666666653,
            84.66666666666653,
            83.66666666666653,
            82.66666666666653,
            83.99999999999986,
            85.33333333333319,
            86.66666666666652,
            85.66666666666652,
            84.66666666666652,
            83.66666666666652,
            82.66666666666652,
            83.99999999999984,
            82.99999999999984,
            81.99999999999984,
            80.99999999999984,
            79.99999999999984,
            78.99999999999984,
            80.33333333333317,
            81.6666666666665,
            82.99999999999983,
            81.99999999999983,
            80.99999999999983,
            79.99999999999983,
            81.33333333333316,
            82.66666666666649,
            81.66666666666649,
            80.66666666666649,
            79.66666666666649,
            78.66666666666649,
            77.66666666666649,
            76.66666666666649,
            75.66666666666649,
            74.66666666666649,
            73.66666666666649,
            72.66666666666649,
            71.66666666666649,
            72.99999999999982,
            74.33333333333314,
            75.66666666666647,
            76.9999999999998,
            78.33333333333313,
            79.66666666666646,
            80.99999999999979
          ]
        }
      }
    },
    "stack_selection_reason": "multi-horizon base LSTM predicts sequences; booster ONNX filters actions using OOF meta-features, tuned thresholds, and final stack metrics"
  },
  "stack_metrics": {
    "base_validation_metrics": {
      "accuracy": 0.4139969488939741,
      "macro_f1": 0.3270441354753808,
      "weighted_f1": 0.45102650020935825,
      "macro_precision": 0.35521739107479416,
      "macro_recall": 0.41629959884048473,
      "confusion_matrix": [
        [
          1370,
          657,
          858
        ],
        [
          27,
          51,
          38
        ],
        [
          1020,
          473,
          750
        ]
      ],
      "classification_report": {
        "DOWN": {
          "precision": 0.5668183698800165,
          "recall": 0.4748700173310225,
          "f1-score": 0.5167861184458695,
          "support": 2885.0
        },
        "SIDEWAYS": {
          "precision": 0.04318374259102455,
          "recall": 0.4396551724137931,
          "f1-score": 0.07864302235929067,
          "support": 116.0
        },
        "UP": {
          "precision": 0.4556500607533414,
          "recall": 0.3343736067766384,
          "f1-score": 0.3857032656209823,
          "support": 2243.0
        },
        "accuracy": 0.4139969488939741,
        "macro avg": {
          "precision": 0.35521739107479416,
          "recall": 0.41629959884048473,
          "f1-score": 0.3270441354753808,
          "support": 5244.0
        },
        "weighted avg": {
          "precision": 0.5076856211888161,
          "recall": 0.4139969488939741,
          "f1-score": 0.45102650020935825,
          "support": 5244.0
        }
      },
      "confidence_ge_threshold_ratio": 0.05415713196033562,
      "trading_proxy": {
        "trade_count": 75,
        "win_rate": 0.6533333333333333,
        "expectancy_r": 0.5377777777777778,
        "profit_factor": 2.6133333333333333,
        "max_drawdown_r": 9.0,
        "equity_curve_tail_r": [
          1.3333333333333333,
          0.33333333333333326,
          1.6666666666666665,
          3.0,
          4.333333333333333,
          5.666666666666666,
          6.999999999999999,
          8.333333333333332,
          9.666666666666666,
          8.666666666666666,
          7.666666666666666,
          6.666666666666666,
          7.999999999999999,
          6.999999999999999,
          6.999999999999999,
          8.333333333333332,
          9.666666666666666,
          8.666666666666666,
          7.666666666666666,
          6.666666666666666,
          5.666666666666666,
          4.666666666666666,
          5.999999999999999,
          7.333333333333332,
          8.666666666666666,
          10.0,
          11.333333333333334,
          12.666666666666668,
          14.000000000000002,
          13.000000000000002,
          14.333333333333336,
          15.66666666666667,
          17.000000000000004,
          18.333333333333336,
          19.666666666666668,
          21.0,
          22.333333333333332,
          23.666666666666664,
          24.999999999999996,
          26.33333333333333,
          27.66666666666666,
          28.999999999999993,
          30.333333333333325,
          31.666666666666657,
          30.666666666666657,
          29.666666666666657,
          30.99999999999999,
          32.33333333333332,
          33.66666666666666,
          34.99999999999999,
          36.33333333333333,
          37.666666666666664,
          39.0,
          40.333333333333336,
          41.66666666666667,
          43.00000000000001,
          44.33333333333334,
          45.66666666666668,
          44.66666666666668,
          43.66666666666668,
          42.66666666666668,
          41.66666666666668,
          40.66666666666668,
          39.66666666666668,
          38.66666666666668,
          37.66666666666668,
          36.66666666666668,
          38.000000000000014,
          37.000000000000014,
          38.33333333333335,
          39.666666666666686,
          41.00000000000002,
          40.00000000000002,
          39.00000000000002,
          40.33333333333336
        ]
      }
    },
    "base_test_metrics": {
      "accuracy": 0.3790045766590389,
      "macro_f1": 0.285727220875645,
      "weighted_f1": 0.4149193904873423,
      "macro_precision": 0.32208686015624227,
      "macro_recall": 0.3527991859340072,
      "confusion_matrix": [
        [
          1017,
          553,
          490
        ],
        [
          43,
          35,
          19
        ],
        [
          691,
          375,
          273
        ]
      ],
      "classification_report": {
        "DOWN": {
          "precision": 0.5808109651627641,
          "recall": 0.4936893203883495,
          "f1-score": 0.533718184203621,
          "support": 2060.0
        },
        "SIDEWAYS": {
          "precision": 0.036344755970924195,
          "recall": 0.36082474226804123,
          "f1-score": 0.0660377358490566,
          "support": 97.0
        },
        "UP": {
          "precision": 0.3491048593350384,
          "recall": 0.20388349514563106,
          "f1-score": 0.25742574257425743,
          "support": 1339.0
        },
        "accuracy": 0.3790045766590389,
        "macro avg": {
          "precision": 0.32208686015624227,
          "recall": 0.3527991859340072,
          "f1-score": 0.285727220875645,
          "support": 3496.0
        },
        "weighted avg": {
          "precision": 0.4769586488026573,
          "recall": 0.3790045766590389,
          "f1-score": 0.4149193904873423,
          "support": 3496.0
        }
      },
      "confidence_ge_threshold_ratio": 0.04891304347826087,
      "trading_proxy": {
        "trade_count": 35,
        "win_rate": 0.2571428571428571,
        "expectancy_r": -0.34285714285714286,
        "profit_factor": 0.5,
        "max_drawdown_r": 21.333333333333336,
        "equity_curve_tail_r": [
          1.3333333333333333,
          2.6666666666666665,
          4.0,
          5.333333333333333,
          6.666666666666666,
          7.999999999999999,
          9.333333333333332,
          8.333333333333332,
          7.333333333333332,
          6.333333333333332,
          5.333333333333332,
          4.333333333333332,
          3.333333333333332,
          4.666666666666665,
          3.666666666666665,
          2.666666666666665,
          1.6666666666666652,
          0.6666666666666652,
          -0.3333333333333348,
          -1.3333333333333348,
          -1.3333333333333348,
          -1.5543122344752192e-15,
          -1.5543122344752192e-15,
          -1.0000000000000016,
          -2.0000000000000018,
          -3.0000000000000018,
          -4.000000000000002,
          -5.000000000000002,
          -6.000000000000002,
          -7.000000000000002,
          -8.000000000000002,
          -9.000000000000002,
          -10.000000000000002,
          -11.000000000000002,
          -12.000000000000002
        ]
      }
    },
    "booster_validation_metrics": {
      "accuracy": 0.8976803304734668,
      "macro_f1": 0.7982984628760603,
      "weighted_f1": 0.9097375240072398,
      "macro_precision": 0.7500831143027004,
      "macro_recall": 0.9072477229782807,
      "confusion_matrix": [
        [
          2517,
          295
        ],
        [
          27,
          308
        ]
      ],
      "classification_report": {
        "SKIP": {
          "precision": 0.9893867924528302,
          "recall": 0.8950924608819346,
          "f1-score": 0.9398805078416729,
          "support": 2812.0
        },
        "ENTER": {
          "precision": 0.5107794361525705,
          "recall": 0.9194029850746268,
          "f1-score": 0.6567164179104478,
          "support": 335.0
        },
        "accuracy": 0.8976803304734668,
        "macro avg": {
          "precision": 0.7500831143027004,
          "recall": 0.9072477229782807,
          "f1-score": 0.7982984628760603,
          "support": 3147.0
        },
        "weighted avg": {
          "precision": 0.9384387580198507,
          "recall": 0.8976803304734668,
          "f1-score": 0.9097375240072398,
          "support": 3147.0
        }
      },
      "confidence_ge_threshold_ratio": 0.1754051477597712,
      "trading_proxy": {
        "trade_count": 552,
        "win_rate": 0.5253623188405797,
        "expectancy_r": 0.22584541062801927,
        "profit_factor": 1.475826972010178,
        "max_drawdown_r": 33.33333333333332,
        "equity_curve_tail_r": [
          130.33333333333326,
          129.33333333333326,
          128.33333333333326,
          127.33333333333326,
          126.33333333333326,
          125.33333333333326,
          124.33333333333326,
          123.33333333333326,
          122.33333333333326,
          121.33333333333326,
          120.33333333333326,
          119.33333333333326,
          118.33333333333326,
          117.33333333333326,
          116.33333333333326,
          115.33333333333326,
          114.33333333333326,
          113.33333333333326,
          112.33333333333326,
          111.33333333333326,
          110.33333333333326,
          109.33333333333326,
          108.33333333333326,
          109.66666666666659,
          110.99999999999991,
          112.33333333333324,
          111.33333333333324,
          112.66666666666657,
          113.9999999999999,
          115.33333333333323,
          116.66666666666656,
          115.66666666666656,
          114.66666666666656,
          113.66666666666656,
          114.99999999999989,
          116.33333333333321,
          115.33333333333321,
          114.33333333333321,
          115.66666666666654,
          116.99999999999987,
          115.99999999999987,
          114.99999999999987,
          113.99999999999987,
          112.99999999999987,
          114.3333333333332,
          115.66666666666653,
          116.99999999999986,
          118.33333333333319,
          119.66666666666652,
          120.99999999999984,
          122.33333333333317,
          121.33333333333317,
          120.33333333333317,
          119.33333333333317,
          118.33333333333317,
          117.33333333333317,
          116.33333333333317,
          115.33333333333317,
          114.33333333333317,
          115.6666666666665,
          116.99999999999983,
          118.33333333333316,
          119.66666666666649,
          120.99999999999982,
          122.33333333333314,
          123.66666666666647,
          124.9999999999998,
          126.33333333333313,
          127.66666666666646,
          128.9999999999998,
          127.9999999999998,
          129.33333333333314,
          130.6666666666665,
          131.99999999999983,
          133.33333333333317,
          132.33333333333317,
          131.33333333333317,
          130.33333333333317,
          131.66666666666652,
          132.99999999999986,
          134.3333333333332,
          133.3333333333332,
          132.3333333333332,
          131.3333333333332,
          130.3333333333332,
          129.3333333333332,
          128.3333333333332,
          127.3333333333332,
          126.3333333333332,
          127.66666666666653,
          126.66666666666653,
          125.66666666666653,
          126.99999999999986,
          128.3333333333332,
          127.3333333333332,
          126.3333333333332,
          125.3333333333332,
          124.3333333333332,
          123.3333333333332,
          124.66666666666653
        ]
      },
      "tuned_confidence_threshold": 0.67,
      "tuned_min_confidence_edge": 0.0
    },
    "combined_validation_metrics": {
      "accuracy": 0.9487032799389779,
      "macro_f1": 0.784655681526918,
      "weighted_f1": 0.9546888488563503,
      "macro_precision": 0.733326328371734,
      "macro_recall": 0.8761738085702844,
      "confusion_matrix": [
        [
          4776,
          218
        ],
        [
          51,
          199
        ]
      ],
      "classification_report": {
        "SKIP": {
          "precision": 0.9894344313238036,
          "recall": 0.9563476171405687,
          "f1-score": 0.9726097138784238,
          "support": 4994.0
        },
        "ENTER": {
          "precision": 0.47721822541966424,
          "recall": 0.796,
          "f1-score": 0.5967016491754122,
          "support": 250.0
        },
        "accuracy": 0.9487032799389779,
        "macro avg": {
          "precision": 0.733326328371734,
          "recall": 0.8761738085702844,
          "f1-score": 0.784655681526918,
          "support": 5244.0
        },
        "weighted avg": {
          "precision": 0.9650152758173133,
          "recall": 0.9487032799389779,
          "f1-score": 0.9546888488563503,
          "support": 5244.0
        }
      },
      "confidence_ge_threshold_ratio": 0.06960335621662853,
      "trading_proxy": {
        "trade_count": 365,
        "win_rate": 0.4821917808219178,
        "expectancy_r": 0.1251141552511415,
        "profit_factor": 1.2416225749559084,
        "max_drawdown_r": 35.00000000000004,
        "equity_curve_tail_r": [
          67.66666666666669,
          69.00000000000001,
          70.33333333333334,
          71.66666666666667,
          70.66666666666667,
          69.66666666666667,
          68.66666666666667,
          67.66666666666667,
          66.66666666666667,
          65.66666666666667,
          64.66666666666667,
          63.66666666666667,
          65.0,
          66.33333333333333,
          65.33333333333333,
          64.33333333333333,
          65.66666666666666,
          66.99999999999999,
          68.33333333333331,
          69.66666666666664,
          68.66666666666664,
          67.66666666666664,
          66.66666666666664,
          65.66666666666664,
          64.66666666666664,
          63.66666666666664,
          64.99999999999997,
          66.3333333333333,
          65.3333333333333,
          64.3333333333333,
          63.3333333333333,
          62.3333333333333,
          61.3333333333333,
          62.666666666666636,
          61.666666666666636,
          60.666666666666636,
          59.666666666666636,
          58.666666666666636,
          57.666666666666636,
          56.666666666666636,
          55.666666666666636,
          54.666666666666636,
          53.666666666666636,
          52.666666666666636,
          51.666666666666636,
          52.99999999999997,
          54.33333333333331,
          53.33333333333331,
          52.33333333333331,
          51.33333333333331,
          50.33333333333331,
          49.33333333333331,
          48.33333333333331,
          49.66666666666664,
          50.99999999999998,
          52.333333333333314,
          51.333333333333314,
          50.333333333333314,
          49.333333333333314,
          48.333333333333314,
          47.333333333333314,
          46.333333333333314,
          45.333333333333314,
          44.333333333333314,
          43.333333333333314,
          42.333333333333314,
          41.333333333333314,
          40.333333333333314,
          39.333333333333314,
          40.66666666666665,
          41.999999999999986,
          43.33333333333332,
          44.66666666666666,
          45.99999999999999,
          47.33333333333333,
          48.666666666666664,
          47.666666666666664,
          46.666666666666664,
          48.0,
          47.0,
          48.333333333333336,
          49.66666666666667,
          51.00000000000001,
          50.00000000000001,
          49.00000000000001,
          50.33333333333334,
          51.66666666666668,
          53.000000000000014,
          54.33333333333335,
          53.33333333333335,
          52.33333333333335,
          51.33333333333335,
          50.33333333333335,
          49.33333333333335,
          48.33333333333335,
          47.33333333333335,
          46.33333333333335,
          45.33333333333335,
          44.33333333333335,
          45.666666666666686
        ]
      }
    },
    "combined_test_metrics": {
      "accuracy": 0.9699656750572082,
      "macro_f1": 0.8542634144714667,
      "weighted_f1": 0.9733457410967918,
      "macro_precision": 0.7912992617240304,
      "macro_recall": 0.9612395682194713,
      "confusion_matrix": [
        [
          3253,
          98
        ],
        [
          7,
          138
        ]
      ],
      "classification_report": {
        "SKIP": {
          "precision": 0.9978527607361963,
          "recall": 0.9707549985079081,
          "f1-score": 0.9841173801240357,
          "support": 3351.0
        },
        "ENTER": {
          "precision": 0.5847457627118644,
          "recall": 0.9517241379310345,
          "f1-score": 0.7244094488188977,
          "support": 145.0
        },
        "accuracy": 0.9699656750572082,
        "macro avg": {
          "precision": 0.7912992617240304,
          "recall": 0.9612395682194713,
          "f1-score": 0.8542634144714667,
          "support": 3496.0
        },
        "weighted avg": {
          "precision": 0.9807187462300384,
          "recall": 0.9699656750572082,
          "f1-score": 0.9733457410967918,
          "support": 3496.0
        }
      },
      "confidence_ge_threshold_ratio": 0.06292906178489703,
      "trading_proxy": {
        "trade_count": 220,
        "win_rate": 0.5863636363636363,
        "expectancy_r": 0.3681818181818181,
        "profit_factor": 1.89010989010989,
        "max_drawdown_r": 23.333333333333442,
        "equity_curve_tail_r": [
          84.33333333333331,
          83.33333333333331,
          82.33333333333331,
          81.33333333333331,
          82.66666666666664,
          83.99999999999997,
          85.3333333333333,
          86.66666666666663,
          87.99999999999996,
          89.33333333333329,
          90.66666666666661,
          89.66666666666661,
          90.99999999999994,
          92.33333333333327,
          93.6666666666666,
          94.99999999999993,
          93.99999999999993,
          92.99999999999993,
          91.99999999999993,
          93.33333333333326,
          92.33333333333326,
          91.33333333333326,
          90.33333333333326,
          89.33333333333326,
          88.33333333333326,
          87.33333333333326,
          86.33333333333326,
          85.33333333333326,
          84.33333333333326,
          83.33333333333326,
          82.33333333333326,
          81.33333333333326,
          80.33333333333326,
          79.33333333333326,
          80.66666666666659,
          81.99999999999991,
          83.33333333333324,
          82.33333333333324,
          81.33333333333324,
          82.66666666666657,
          83.9999999999999,
          85.33333333333323,
          86.66666666666656,
          87.99999999999989,
          89.33333333333321,
          90.66666666666654,
          91.99999999999987,
          93.3333333333332,
          94.66666666666653,
          93.66666666666653,
          92.66666666666653,
          91.66666666666653,
          90.66666666666653,
          89.66666666666653,
          88.66666666666653,
          87.66666666666653,
          86.66666666666653,
          85.66666666666653,
          84.66666666666653,
          83.66666666666653,
          82.66666666666653,
          83.99999999999986,
          85.33333333333319,
          86.66666666666652,
          85.66666666666652,
          84.66666666666652,
          83.66666666666652,
          82.66666666666652,
          83.99999999999984,
          82.99999999999984,
          81.99999999999984,
          80.99999999999984,
          79.99999999999984,
          78.99999999999984,
          80.33333333333317,
          81.6666666666665,
          82.99999999999983,
          81.99999999999983,
          80.99999999999983,
          79.99999999999983,
          81.33333333333316,
          82.66666666666649,
          81.66666666666649,
          80.66666666666649,
          79.66666666666649,
          78.66666666666649,
          77.66666666666649,
          76.66666666666649,
          75.66666666666649,
          74.66666666666649,
          73.66666666666649,
          72.66666666666649,
          71.66666666666649,
          72.99999999999982,
          74.33333333333314,
          75.66666666666647,
          76.9999999999998,
          78.33333333333313,
          79.66666666666646,
          80.99999999999979
        ]
      }
    }
  }
}